README.txt
setup.py
journaltocs/__init__.py
journaltocs.egg-info/PKG-INFO
journaltocs.egg-info/SOURCES.txt
journaltocs.egg-info/dependency_links.txt
journaltocs.egg-info/top_level.txt