Metadata-Version: 1.0
Name: journaltocs
Version: 0.1
Summary: A python wrapper for the JournalTOCs API (http://www.journaltocs.ac.uk/).
Home-page: http://bitbucket.org/simongreenhill/journaltocsapi
Author: Simon Greenhill
Author-email: simon@simon.net.nz
License: BSD
Keywords: JournalTOCs webservice
Platform: UNKNOWN
Classifier: Programming Language :: Python
Classifier: Intended Audience :: Science/Research
Classifier: License :: OSI Approved :: BSD License
Classifier: Topic :: Scientific/Engineering
Classifier: Topic :: Software Development :: Libraries :: Python Modules
